invpy_libs/__init__.py
invpy_libs/isup.py
invpy_libs/parse_csv.py
invpy_libs/workbooks_dict.py
invpy_libs-0.4.2.dist-info/DESCRIPTION.rst
invpy_libs-0.4.2.dist-info/METADATA
invpy_libs-0.4.2.dist-info/RECORD
invpy_libs-0.4.2.dist-info/WHEEL
invpy_libs-0.4.2.dist-info/metadata.json
invpy_libs-0.4.2.dist-info/top_level.txt
