Metadata-Version: 2.0
Name: invpy-libs
Version: 0.4.2
Summary: Inventory automation libraries servers list
Home-page: https://github.com/pablodav/invpy_libs.git
Author: Pablo Estigarribia
Author-email: pablodav@gmail.com
License: gplv3
Platform: UNKNOWN
Requires-Dist: openpyxl
